{"42": ["Solidar", "Johanna Scortea", "Gruppv\u00e5ldtogs I Fittja", "SHL", "Anna Kournikova", "Arrhult", "Lars Ulvenstam", "Hockeyallsvenskan", "Fittja", "Elisabeth Massi Fritz", "jul", "Per Gessle", "Mandelmann", "Anna Holmlund", "God jul", "Allt f\u00f6r Sverige", "Vintersolst\u00e5ndet", "Ted G\u00e4rdestad", "Matts Olsson", "Dylan Allt F\u00f6r Sverige"], "43": ["Bitcoin cash", "Anna Kurnikovov\u00e1", "Enrique Iglesias", "Zden\u011bk Ondr\u00e1\u010dek", "Layers of Fear", "\u0160pindl", "programov\u00e9 prohl\u00e1\u0161en\u00ed vl\u00e1dy", "Petra Krmelov\u00e1", "Jan \u0160efl", "Tom\u00e1\u0161 Klus", "V\u00e1no\u010dn\u00ed P\u0159\u00e1n\u00ed", "Josef Pe\u0161ice", "Jordan", "Ji\u0159\u00ed Hynek", "Inkluze", "Olympi\u00e1da 2018", "Vesni\u010dko m\u00e1 st\u0159ediskov\u00e1", "V\u00e1clav Havel", "Pavel Br\u00e1zda", "Marek Eben"], "49": ["Bitcoin Cash", "Radius", "Tom Cruise", "Top Gun", "Sound Of Music", "Julie Andrews", "Anna Kournikova", "Jumanji", "Christopher Plummer", "Rose McGowan", "Mark Salling", "The Book Of Mormon", "Topgun", "Meghan Markle", "K\u00e5re Schultz", "Tenerife", "Slenderman", "Kobe Bryant", "Mitsubishi", "Gl\u00e6delig jul"], "52": ["Arsenal vs West Ham", "Arsenal F.c.", "Man City", "Manchester City F.c.", "December Global Festivities", "OLIC 4", "PENGASSAN Strike", "Premier League Top Scorer", "Manchester United F.c.", "Man City vs Tottenham", "Man City", "Arsenal F.c.", "Chelsea vs Southampton", "Real Madrid vs Gremio", "Burna Boy", "Net Neutrality", "Eminem Revival", "pornography", "Omarosa", "Premier League table"], "24": ["Ufak Tefek Cinayetler Son B\u00f6l\u00fcm Izle", "Mustafa Cengiz", "Arda Turan", "E\u015fkiya D\u00fcnyaya H\u00fck\u00fcmdar Olmaz Izle", "Fenerbah\u00e7e K\u0131z\u0131ly\u0131ld\u0131z", "H\u00fcseyin \u00c7apk\u0131n", "Manchester City", "Kurtulu\u015f Tokcan", "YEMEN", "\u00c7ukur 9 B\u00f6l\u00fcm Izle", "\u00c7ukur 9. B\u00f6l\u00fcm", "S\u00f6z 26 B\u00f6l\u00fcm", "Spor Toto", "Siyah Beyaz A\u015fk 10 B\u00f6l\u00fcm Izle", "Danla Bilic", "G\u00fcnay G\u00fcner", "K\u0131v\u0131lc\u0131m Ural", "Mara\u015f Katliam\u0131", "Lada", "Humble Bundle"], "25": ["Cavs vs Bucks", "Mackenzie Foy", "Oceans 8", "Kobe Bryant", "Tax Reform Philippines 2017 Update", "TRAIN tax reform", "Tax Reform", "Han Seo Hee", "Seasonal Affective Disorder", "allkpop", "Logan", "Jonghyun", "December Global Festivities", "Min Hyo Rin", "carbon monoxide poisoning", "Biliran", "Taemin", "Christmas Greetings", "Beauty and the Beast", "White"], "26": ["Ot Gala 8", "Betis", "Cepeda", "Argentina", "League of Legends", "Kobe Bryant", "fiestas navide\u00f1as", "Jonghyun", "Ed Sheeran", "Enrique Iglesias", "La Sexta", "Ed Sheeran Perfect", "Fake", "Daniella Semaan", "Griezmann", "Paulinho", "Islandia", "Ines Arrimadas", "Titanic", "Charles Manson"], "27": ["Georgina Rodriguez", "FAUSTO BRIZZI", "Antonia Klugmann", "Napoli Udinese", "Spelacchio", "Ciciretti", "Quasi amici", "Carta del docente", "Michele Placido", "Anastasia", "Ogni maledetto Natale", "Grey S Anatomy 14", "Silvan", "Bellomo", "Asessuale", "Napoli velata", "Kobe Bryant", "Francesca Sofia Novello", "Mia moglie \u00e8 una strega", "auguri di Buon Natale"], "21": ["Pirata de Culiacan", "Jeremy Menez", "Nemesio Oseguera Cervantes", "Marlene Favela", "League of Legends", "Titanic", "Sorteo Uabc", "Kobe Bryant", "fiestas navide\u00f1as", "Jonghyun", "La Voz Mexico", "Enrique Iglesias", "Alma Cero", "Felices Fiestas", "Frases De Navidad", "Beca Salario", "Verificacion", "18 de diciembre", "Laura Pausini", "Oswaldo Alanis"], "48": ["\u03a0\u0391\u039f\u039a", "Euroleague", "\u039a\u03c5\u03c0\u03b5\u03bb\u03bb\u03bf \u0395\u03bb\u03bb\u03b1\u03b4\u03bf\u03c3", "\u03a5\u03b4\u03c1\u03bf\u03c7\u03bb\u03c9\u03c1\u03b9\u03ba\u03bf \u039f\u03be\u03c5", "\u03a7\u03c1\u03ae\u03c3\u03c4\u03bf\u03c2 \u0396\u03b1\u03c0\u03b1\u03bd\u03c4\u03b9\u03ce\u03c4\u03b7\u03c2", "\u03a4\u03b1\u03c3\u03bf\u03c3 \u03a3\u03c4\u03b5\u03c6\u03b1\u03bd\u03bf\u03c5", "Survival Secret", "Kobe Bryant", "\u039d\u03b1\u03bd\u03b1 \u0392\u03b5\u03bd\u03b5\u03c4\u03b7", "\u0395\u03c5\u03c1\u03c9\u03bb\u03b9\u03b3\u03ba\u03b1", "Anna Kournikova", "\u03a4\u03a3\u039c\u0395\u0394\u0395", "\u03ba\u03b1\u03bb\u03ad\u03c2 \u03b3\u03b9\u03bf\u03c1\u03c4\u03ad\u03c2", "\u03a4\u03b5\u03bb\u03b7 2018", "\u039f\u03b9\u03ba\u03bf\u03b3\u03b5\u03bd\u03b5\u03b9\u03b1\u03ba\u03bf \u0395\u03c0\u03b9\u03b4\u03bf\u03bc\u03b1", "Jonghyun", "\u0395\u03bb\u03b5\u03bd\u03b7 \u03a7\u03b5\u03c1\u03bf\u03c5\u03b2\u03b5\u03b9\u03bc", "\u03a7\u03b5\u03c1\u03bf\u03c5\u03b2\u03b5\u03b9\u03bc \u0395\u03bb\u03b5\u03bd\u03b7", "\u03a3\u03c5\u03bd\u03c4\u03b1\u03be\u03b5\u03b9\u03c3 \u0399\u03b1\u03bd\u03bf\u03c5\u03b1\u03c1\u03b9\u03bf\u03c5 2018", "\u0395\u03a0\u0399\u0394\u039f\u039c\u0391 \u0398\u0395\u03a1\u039c\u0391\u039d\u03a3\u0397\u03a3 2018"], "23": ["\uc9c0\uc608", "\uc2e0\uacfc\ud568\uaed8-\uc8c4\uc640 \ubc8c", "\uae08\uc624\uacf5\ub300", "\uc885\ud604 \uc720\uc11c", "\uc720\ube57", "\uc0e4\uc774\ub2c8 \uc885\ud604", "\uc228\uc740 \ubcf4\ud5d8\uae08", "Jonghyun", "\uc885\ud604 \uc0ac\ub9dd", "\ubbfc\ud6a8\ub9b0", "\ucd5c\uc11c\uc778", "\ud000\ud140", "\uac08\ud0c4", "\ub098\uc05c \ub140\uc11d \ub4e4 \uc545\uc758 \ub3c4\uc2dc", "\ub958\uc5ec\ud574", "\uc774\ub300\ubaa9\ub3d9\ubcd1\uc6d0", "\ucd95\uad6c", "\uc720\uc778\uc601", "\ud55c\uc77c\uc804", "\ub098\uc05c\ub140\uc11d\ub4e4"], "46": ["Bitcoin Cash", "Werner De Schepper", "Roger Federer", "Ines Arrimadas", "Marion Bartoli", "Ugg Boots", "Bitcoin News", "Anna Kournikova", "Mirja du Mont", "Courchevel", "Dfb Pokal", "Mark Salling", "Daniel Regli", "Kobe Bryant", "Matthew Petersen", "Kev Adams", "Nordahl Lelandais", "Mortal Engines", "Brokat", "The Voice of Germany 2017"], "47": ["Marcelo Rio Ave", "Bitcoin Cash", "Anitta", "Lolita", "Salario Minimo 2017", "Anna Kournikova", "Rose McGowan", "Luciana Abreu", "Manchester City", "Georgina Rodriguez", "Susana Vieira", "Clark Gregg", "Mortal Engines", "John John Florence", "Celeste Rodrigues", "Boas Festas", "FC Porto", "Ta\u00e7a de Portugal", "Jonghyun", "Feliz Natal"], "44": ["Bitcoin Cash", "Franz Beckenbauer", "\u00d63 Weihnachtswunder", "Alexander H\u00f6ferl", "Anna Kournikova", "Mirja du Mont", "Jack the Ripper", "Dfb Pokal", "Courchevel", "Launsky Tieffenthal", "Gisela Perez de Acha", "Neue Regierung \u00d6sterreich 2017", "Christbaum Rom", "Steinhoff", "Gudenus", "Hermann Maier", "Anne Sophie Briest", "Matthew Petersen", "Verge", "S\u00fcdtirol"], "45": ["Oxenfree", "Enrique Iglesias", "Cristiano Ronaldo", "Layers of Fear", "Tenki R\u00e9ka", "Mortal Engines", "Kobe Bryant", "Jonghyun", "Ninja Warrior", "boldog kar\u00e1csonyt", "Retro R\u00e1di\u00f3", "H\u00f3di Pamela", "Celeb Vagyok Ments Ki Innen Gy\u0151ztese", "Stohl Luca", "Simonka Csaba", "K\u00e9kestet\u0151", "Sz\u00e9khelyi J\u00f3zsef", "T\u00fcnd\u00e9rk\u00f6r Alap\u00edtv\u00e1ny", "Rose McGowan", "HELLP szindr\u00f3ma"], "28": ["\u0110\u00e0 L\u1ea1t c\u00f3 tuy\u1ebft", "Phan \u0110\u00ecnh \u0110\u1ee9c", "bitcoin cash", "VLTKm", "Vu An Giet Chong O Binh Duong", "Taeyeon", "tr\u1ea7m c\u1ea3m", "b\u1ec7nh tr\u1ea7m c\u1ea3m", "Chuy\u1ec7n anh v\u1eabn ch\u01b0a k\u1ec3", "H\u1ed3ng T\u01a1", "Jonghyun", "v\u1ee3 gi\u1ebft ch\u1ed3ng \u1edf B\u00ecnh D\u01b0\u01a1ng", "Taeyang", "Jonghyun Ch\u1ebft", "\u0110\u1ea1i \u0110\u01b0\u1eddng V\u00f5 L\u00e2m", "Nhi\u1ec7t \u0111\u1ed9", "Kim Joo Hyuk", "Yugi H5", "nh\u00e0n", "Vu An Chat Dau O Binh Duong"], "29": ["\u0645\u0627\u0646\u0634\u0633\u062a\u0631 \u0633\u064a\u062a\u064a", "\u0646\u062a\u064a\u062c\u0629 \u0645\u0628\u0627\u0631\u0627\u0629 \u0627\u0644\u0627\u0633\u0645\u0627\u0639\u064a\u0644\u0649 \u0627\u0644\u064a\u0648\u0645", "\u062d\u0627\u062f\u062b \u0645\u0637\u0627\u0631 \u0627\u0644\u0639\u0631\u064a\u0634", "\u0627\u0633\u062a\u0647\u062f\u0627\u0641 \u0645\u0637\u0627\u0631 \u0627\u0644\u0639\u0631\u064a\u0634", "\u062f\u0627\u0644\u064a\u0627 \u062e\u0648\u0631\u0634\u064a\u062f", "\u0627\u0644\u0627\u0633\u0645\u0627\u0639\u064a\u0644\u0649", "\u0639\u0647\u062f \u0627\u0644\u062a\u0645\u064a\u0645\u064a", "\u0635\u0627\u0644\u062d \u062c\u0645\u0639\u0629", "\u0631\u0646\u064a\u0645 \u0627\u0644\u0648\u0644\u064a\u0644\u064a", "\u0645\u062d\u0645\u062f \u0628\u0646 \u0633\u0644\u0645\u0627\u0646 \u0628\u0646 \u0639\u0628\u062f \u0627\u0644\u0639\u0632\u064a\u0632 \u0622\u0644 \u0633\u0639\u0648\u062f", "\u0642\u0646\u0627\u0629 \u0627\u0644\u0633\u0648\u064a\u0633", "\u0628\u0648\u064a\u0643\u0627", "\u0623\u062d\u0645\u062f \u0623\u0628\u0648 \u0647\u0634\u064a\u0645\u0629", "\u0627\u0644\u0627\u0633\u0645\u0627\u0639\u064a\u0644\u064a", "\u0627\u064a\u062c\u0644 \u0643\u0627\u0628\u064a\u062a\u0627\u0644", "SHINee", "\u0645\u0633\u0644\u0633\u0644 \u0627\u0644\u0637\u0648\u0641\u0627\u0646 \u0627\u0644\u062d\u0644\u0642\u0629 44", "\u0646\u0627\u062f\u064a \u0644\u064a\u0641\u0631\u0628\u0648\u0644", "\u0645\u0628\u0627\u0631\u0627\u0629 \u0644\u064a\u0641\u0631\u0628\u0648\u0644", "\u0647\u062f\u0641 \u0645\u062d\u0645\u062f \u0635\u0644\u0627\u062d \u0627\u0644\u0627\u062e\u064a\u0631"], "40": ["Arsenal", "Man City", "Manchester City F.c.", "Michelle Molatlou", "Mamelodi Sundowns", "Jonghyun", "Cyril Ramaphosa", "eNCA", "Paul Mashatile", "Euro To Rand", "Ewn", "Pound To Rand", "Gwede Mantashe", "Julius Malema", "Senzo Mchunu", "News 24 Latest", "DD Mabuza", "Sabc News", "Enca News", "ANC election results"], "41": ["Koers Bitcoin", "Manchester City", "Marion Bartoli", "Lindsay", "Bitcoin Cash", "Anna Kournikova", "Cap Vert", "Michel Sardou", "Henri PFR", "Greenyard", "Manifestation Bruxelles", "Arsenal", "Hayden Christensen", "Borsalino", "Le Meilleur P\u00e2tissier 2017", "Mortal Engines", "Kobe Bryant", "Joyeuses F\u00eates !", "De Warmste Week", "Jonghyun"], "1": ["Joe Budden", "Heather North", "El Pirata de Culiacan", "Tax Bill", "Bitcoin Cash", "Sia", "Oceans 8", "TJ Miller", "Demi Lovato", "UFO", "Andrea Nicole Baber", "Sicario 2", "Anna Kendrick", "Charlie Puth", "Kelly Clarkson", "UGG", "Lane Kiffin", "Eva Longoria", "CIA", "Catt Sadler"], "3": ["Mi.com", "Bitcoin News", "Okinawa Praise Electric Scooter", "Samsung Galaxy A8", "Jayalalitha Video", "Delhi metro", "Delhi Police Answer Key 2017", "Milind Soman", "Sani Peyarchi 2017", "Aiyaary", "Keerthi Suresh", "South Indian Bank", "Gujarat Election Result", "December Global Festivities", "Aaj Tak", "News", "Ndtv", "Indian National Congress", "Times Of India", "\u0917\u0941\u091c\u0930\u093e\u0924 \u091a\u0941\u0928\u093e\u0935 \u092a\u0930\u093f\u0923\u093e\u092e"], "5": ["Bitcoin Cash", "Man City", "Carabao Cup", "Oceans 8", "COE", "Kobe Bryant", "carbon monoxide poisoning", "Shinee Jonghyun Funeral", "Everton", "Amtrak", "27 Club", "Jonghyun", "Gujarat elections", "allkpop", "Taeyang", "Times Of India", "Taemin", "Merry Christmas", "ITE", "White"], "4": ["\u5317\u6d77\u9053 \u5730\u9707", "\u7d30\u5ddd\u3075\u307f\u3048", "\u6b66\u8c4a", "\u95a2\u5149\u5f66", "\u5b89\u5ba4\u5948\u7f8e\u6075", "\u6771\u65b9\u795e\u8d77", "\u677e\u5ca1\u8309\u512a", "\u6850\u8c37\u7f8e\u73b2", "\u5927\u9d6c", "M\u30b9\u30c6", "\u30b5\u30f3\u30c9\u30a6\u30a3\u30c3\u30c1\u30de\u30f3", "\u30b7\u30e7\u30fc\u30f3K", "\u9ad8\u6a4b\u3072\u304b\u308b", "\u30b8\u30e7\u30f3\u30d2\u30e7\u30f3", "\u4e0a\u91ce\u52d5\u7269\u5712", "\u30df\u30f3\u30d2\u30e7\u30ea\u30f3", "\u4eca\u7530\u7f8e\u685c", "\u6709\u99ac\u8a18\u5ff5", "\u30a6\u30fc\u30de\u30f3\u30e9\u30c3\u30b7\u30e5\u30a2\u30ef\u30fc", "\u76f4\u864e"], "6": ["\u05e2\u05d4\u05d3 \u05ea\u05de\u05d9\u05de\u05d9", "\u05e9\u05dc\u05de\u05d4 \u05d0\u05e8\u05e6\u05d9 \u05d5\u05e2\u05d5\u05de\u05e8 \u05d0\u05d3\u05dd", "\u05e0\u05d1\u05d9 \u05e1\u05d0\u05dc\u05d7", "\u05d6\u05d0\u05ea \u05d7\u05e0\u05d5\u05db\u05d4", "\u05e2\u05d0\u05d4\u05d3 \u05ea\u05de\u05d9\u05de\u05d9", "\u05e2\u05e8\u05d5\u05e5 20", "\u05de\u05db\u05d1\u05d9 \u05ea\u05dc \u05d0\u05d1\u05d9\u05d1 \u05db\u05d3\u05d5\u05e8\u05e1\u05dc", "\u05e2\u05d5\u05de\u05e8 \u05d0\u05d3\u05dd", "Jonghyun", "\u05d4\u05d1\u05d5\u05d6\u05d2\u05dc\u05d5\u05e1 \u05e4\u05e8\u05e7 14", "\u05de\u05d9\u05db\u05d0\u05dc \u05de\u05d5\u05e8", "\u05d1\u05d9\u05ea \u05e8 \u05d9\u05e8\u05d5\u05e9\u05dc\u05d9\u05dd", "\u05d0\u05d9\u05d9\u05dc \u05d1\u05e8\u05e7\u05d5\u05d1\u05d9\u05e5", "\u05e1\u05d8\u05d8\u05d5\u05e1\u05d9\u05dd \u05de\u05e6\u05d9\u05d9\u05e6\u05d9\u05dd", "\u05d0\u05d5\u05e4\u05d9\u05e8\u05d4 \u05d0\u05e1\u05d9\u05d9\u05d2", "\u05e7\u05d5\u05e4\u05d9\u05e7\u05e1", "\u05de\u05db\u05d1\u05d9 \u05e0\u05ea\u05e0\u05d9\u05d4", "\u05d4\u05d3\u05dc\u05e7\u05ea \u05e0\u05e8\u05d5\u05ea \u05d7\u05e0\u05d5\u05db\u05d4", "\u05d8\u05d1\u05e2", "\u05de\u05e2\u05d5\u05d6 \u05e6\u05d5\u05e8"], "9": ["Bitcoin Cash", "Man City", "Arsenal", "Arthur Collins", "Oceans 8", "U2", "The Killers", "Mortal Engines", "Manchester City F.c.", "seal", "Shamed", "Arsenal F.c.", "Anna Kournikova", "Miranda Hart", "Matt Damon", "Paul Lim", "Cameron House", "Jonghyun", "Terence Beesley", "RAF Mildenhall"], "8": ["Jarryd Hayne", "Oceans 8", "Bom Sydney", "Arsenal", "Hugh Jackman", "Cardi B", "Brisbane Heat", "Rose McGowan", "Isaac Emmanuel Roberts", "Man City", "James Corden", "John John Florence", "Big Bash", "Bom Melbourne", "bitcoin cash", "Anna Kournikova", "Power Outage", "SACE", "Kobe Bryant", "Mortal Engines"], "51": ["bitcoin cash", "Arsenal", "Krystallsyken", "First House", "Frode Berg", "Kristine Ulleb\u00f8", "Norske Skog", "Anna Kournikova", "Ragnhild Mowinckel", "Jonathan Rhys Meyers", "jul", "Marie Blokhus", "Sjetne skole", "Amalie Iuel", "Siri Kristiansen", "Bjarne Berntsen", "Chateau Louis XIV", "Vm Finale H\u00e5ndball 2017", "Nora M\u00f8rk", "Finale H\u00e5ndball Vm 2017"], "39": ["Ignatul", "Mihai Lucan", "Tudorel Toader", "Jennifer Lawrence", "Marian Ralea", "Anna Kournikova", "Seful SRI Prahova", "Carmen Serban", "Uber", "Parcul Herastrau", "Eugen Nicolicea", "Horoscop 19 decembrie 2017", "Palatul Elisabeta", "Timisoara Dinamo", "HOROSCOP 20 decembrie 2017", "Jumanji", "Ilan Laufer", "Salariul Minim 2018", "MONARHIE", "Silviu Deatcu"], "38": ["Pirata de Culiacan", "Manchester City", "Anna Kournikova", "Mon Laferte", "Arsenal", "Alexis Sanchez", "League of Legends", "Reinaldo Rueda", "Argentina", "Luis Miguel", "Ariel Holan", "Cristiano Ronaldo", "La suerte de ser chileno", "Jonghyun", "fiestas navide\u00f1as", "Halo solar", "Ahora Noticias", "Circulo En El Sol", "Bolsa de Santiago", "Arcoiris Alrededor Del Sol"], "10": ["\u5f35\u5982\u57ce", "\u66f9\u8cb4\u5b50", "\u5800\u5317\u771f\u5e0c", "Bitcoin Cash", "\u9418 \u9249 \u907a\u66f8", "\u8b5a\u8000\u5b97", "\u738b\u70b3\u5fe0", "\u4e2d\u9280\u7d00\u5ff5\u9214", "\u5510\u6587\u9f8d", "Kobe Bryant", "\u7533\u4e16\u666f", "\u6291\u9b31\u75c7", "\u5929\u751f\u6a13", "\u9678\u6c38", "\u8d99\u8587", "\u9ece\u5df4\u5ae9", "\u80a2\u89e3", "Shinee", "\u9594\u5b5d\u7433", "Jonghyun"], "13": ["Sicario 2", "Titanic", "CIA", "Toronto Maple Leafs", "Edmonton Oilers", "Drive Bc", "Oceans 8", "Bitcoin Cash", "Who Won The Voice 2017", "Burrard Bridge", "TJ Miller", "The Office", "TransLink", "Demi Lovato", "embolie pulmonaire", "Rose McGowan", "Nanaimo Weather", "Anna Kendrick", "Eva Longoria", "Kelly Clarkson"], "12": ["\u674e\u6bd3\u82ac", "\u5927\u5a1b\u6a02\u5bb6", "\u5168\u5bb6 \u623d\u6597", "\u5f6d\u66c9\u5f64", "Airpods", "\u96ea\u78a7", "\u9673\u6c0f\u74ca\u5b89", "\u5802\u5a1c", "\u91d1\u67f1\u8d6b", "\u5b54\u4ee4\u5947", "\u885d\u7a81\u4e16\u754c", "\u9673\u83ca", "\u738b\u70b3\u5fe0", "\u937e \u9249 \u907a\u66f8", "Kobe Bryant", "\u7533\u4e16\u666f", "\u9f8d\u767c\u5802", "\u9418\u9249 \u907a\u66f8", "\u592a\u598d", "\u91d1\u6210\u73c9"], "15": ["Mirja du Mont", "Kevin M\u00fcnch", "Simon Terodde", "Bitcoin Cash", "Gerd M\u00fcller", "Dfb Pokal", "Anna Kournikova", "Franz Beckenbauer", "Anne Sophie Briest", "VfB Stuttgart", "Numerus clausus", "\u00d6ffnungszeiten", "Wer wird Million\u00e4r", "Supertalent", "Paul Lim", "Mortal Engines", "SC Paderborn", "Breitscheidplatz", "Der Bergdoktor", "Dfb Pokal Heute"], "14": ["\u0414\u0435\u043d\u044c \u0424\u0441\u0431", "\u0401\u043b\u043a\u0438 \u043d\u043e\u0432\u044b\u0435", "20 \u0414\u0435\u043a\u0430\u0431\u0440\u044f \u041f\u0440\u0430\u0437\u0434\u043d\u0438\u043a", "\u0414\u0435\u043d\u044c \u0421\u0432\u044f\u0442\u043e\u0433\u043e \u041d\u0438\u043a\u043e\u043b\u0430\u044f", "\u0410\u043d\u043d\u0430 \u041a\u0443\u0440\u043d\u0438\u043a\u043e\u0432\u0430", "Feduk", "\u041b\u0435\u043d\u0438\u043d\u0433\u0440\u0430\u0434 46", "\u0421\u0432\u044f\u0442\u043e\u0439 \u041d\u0438\u043a\u043e\u043b\u0430\u0439", "\u0414\u0436\u043e\u043d\u0445\u0451\u043d", "\u0412\u0435\u0440\u0441\u0442\u043e\u0432", "\u0420\u043e\u0441\u0441\u0438\u044f \u0424\u0438\u043d\u043b\u044f\u043d\u0434\u0438\u044f \u0425\u043e\u043a\u043a\u0435\u0439", "\u0433\u043e\u0440\u043e\u0441\u043a\u043e\u043f \u043d\u0430 2018 \u0433\u043e\u0434", "\u0420\u043e\u0434\u0438\u043e\u043d \u0429\u0435\u0434\u0440\u0438\u043d", "\u0411\u0440\u044d\u0434 \u041f\u0438\u0442\u0442", "\u0420\u043e\u0441\u0441\u0438\u044f \u041a\u0430\u043d\u0430\u0434\u0430", "\u0411\u0438\u0442\u0432\u0430 \u042d\u043a\u0441\u0442\u0440\u0430\u0441\u0435\u043d\u0441\u043e\u0432 16.12 17", "\u0410\u043b\u0435\u043a\u0441\u0430\u043d\u0434\u0440 \u041c\u043e\u0445\u043e\u0432", "\u0423\u043b\u044e\u043a\u0430\u0435\u0432", "\u041f\u0440\u043e\u043c\u0441\u0432\u044f\u0437\u044c\u0431\u0430\u043d\u043a", "\u041f\u043e\u0432\u0435\u0442\u043a\u0438\u043d"], "17": ["bitcoin", "Concert at SEA", "Yvonne van Gennip", "Top 2000", "Anna Kournikova", "KNVB beker", "Sportgala 2017", "bitcoin cash", "Een Huis Vol", "Pechtold", "Anna Nooshin", "Heleen van Royen", "designated survivor", "als", "Paul Lim", "Anouk", "Willem 2", "Glazen Huis Apeldoorn", "Serious Request 2017", "Jonghyun"], "16": ["Indochine", "Network Lille", "Les Derniers Jedi", "Euromillions 19 Decembre 2017", "Jennifer Lawrence", "Marion Bartoli", "Hayden Christensen", "Rokhaya Diallo", "Arielle Dombasle", "Charlotte Gainsbourg", "Anna Kournikova", "Star Wars 2", "Marave challenge", "Franck de Lapersonne", "Sonia Krimi", "Eddy de Pretto", "Manchester City", "embolie pulmonaire", "Scope Sant\u00e9", "Patagonie"], "19": ["Redmi 5A", "Ruben Onsu Ayu Ting Ting", "LGBT", "Jumanji", "Manchester City F.c.", "Farah Quinn", "Piala Liga Inggris", "Panglima Tni Jenderal Gatot Nurmantyo", "Aliando Syarief Siapa Takut Jatuh Cinta", "Carlos Tevez", "Han Seo Hee", "Squishy", "Tapir", "Tanda Tangan Jokowi", "Tata Janeeta", "Kurt Cobain", "Hak Veto", "Kim Jong Un", "Jonghyun SHINee", "perayaan global di bulan Desember"], "18": ["Manchester City", "Gazeta Online", "MC Livinho", "Mega Sena 1998", "C\u00e9cile Loreen", "Animale", "Secretaria da Educa\u00e7\u00e3o", "Cederj", "Larissa Manoela Na Globo", "Natalia Do Vale", "G1 RN", "Marcelo Odebrecht", "Suzana Vieira", "cobra", "Greve De Onibus Es", "Arsenal", "Lulu Santos", "Diego Luna", "19 de dezembro", "Edital Tj Sp Interior"], "31": ["Henryk Cioch", "Manchester City", "bitcoin cash", "Ma\u0142gorzata Godlewska", "Stanis\u0142aw Kogut", "Przystanek \u0141oso\u015b", "Anna Kurnikowa", "Sza\u0142 uniesie\u0144", "Norwegia", "World in Conflict", "Oxenfree", "Www Wp Pl", "Dominika Gwit", "Kartuzy Info", "Dawid Celt", "Szwecja", "Ocean S 8", "Aleksandra Pop\u0142awska", "Puchar Niemiec", "Kobe Bryant"], "30": ["Pirata de Culiacan", "Infobae", "Clarin", "Cristobal Lopez", "Camila Morrone", "MinutoUno", "Policia Muerto Hoy", "Votacion Reforma Previsional", "Ingrid Grudke", "Lucas Pratto", "Radio Mitre En Vivo", "Leopoldo Moreau", "Discurso De Macri", "Marcelo Tinelli", "Lacapital", "League of Legends", "El Pais", "Maria Emilia Soria", "Fernando Iglesias", "Reforma Previsional En Vivo"], "37": ["Manchester City F.c.", "Man City", "Arsenal", "GHRIS", "Arsenal F.c.", "Napoli Fc", "Schalke 04", "Napoli", "Everton Results", "Francis Nyenze", "Mamelodi Sundowns", "Neroca FC", "Mainz", "Carlisle Vs Gillingham", "FC Porto", "December Global Festivities", "Everton", "Mainz Fc", "Cyril Ramaphosa", "Thika Garissa Road Accident"], "36": ["\u0632\u064a\u0627\u062f \u0628\u0646 \u0646\u062d\u064a\u062a", "\u0627\u0644\u0645\u0644\u0643 \u0633\u0644\u0645\u0627\u0646", "\u0627\u0644\u0642\u0627\u0636\u064a \u0627\u0644\u062c\u064a\u0631\u0627\u0646\u064a", "\u0645\u0627\u0646\u0634\u0633\u062a\u0631 \u0633\u064a\u062a\u064a", "\u0627\u062e\u0628\u0627\u0631 \u0627\u0644\u064a\u0648\u0645", "\u0645\u0639\u0646 \u0628\u0631\u063a\u0648\u062b", "\u0627\u0644\u0636\u0645\u0627\u0646 \u0627\u0644\u0627\u062c\u062a\u0645\u0627\u0639\u064a \u0627\u0644\u0645\u0642\u0637\u0648\u0639\u0629", "\u0631\u064a\u0645 \u0627\u0644\u0646\u062c\u0645", "\u0633\u0642\u0648\u0637 \u0635\u0627\u0631\u0648\u062e \u0639\u0644\u0649 \u0627\u0644\u0631\u064a\u0627\u0636", "\u0633\u0644\u0645\u0627\u0646 \u0628\u0646 \u0639\u0628\u062f\u0627\u0644\u0639\u0632\u064a\u0632", "\u0647\u0644\u0627 \u0628\u0627\u0644\u062e\u0645\u064a\u0633", "Ballistic Missile", "\u0627\u062e\u0628\u0627\u0631 \u0627\u0644\u0633\u0639\u0648\u062f\u064a\u0629 \u0627\u0644\u064a\u0648\u0645 \u0639\u0627\u062c\u0644 \u0633\u0628\u0642", "\u0623\u062d\u0645\u062f \u0623\u0628\u0648 \u0647\u0634\u064a\u0645\u0629", "\u0627\u0644\u0627\u062e\u0628\u0627\u0631\u064a\u0629", "\u0639\u0643\u0627\u0638", "\u0635\u0627\u0631\u0648\u062e \u0627\u0644\u0631\u064a\u0627\u0636", "\u0645\u064a\u0632\u0627\u0646\u064a\u0629 \u0627\u0644\u0633\u0639\u0648\u062f\u064a\u0629", "\u0648\u0632\u0627\u0631\u0629 \u0627\u0644\u0645\u0627\u0644\u064a\u0629", "\u0645\u064a\u0632\u0627\u0646\u064a\u0629 \u0627\u0644\u0633\u0639\u0648\u062f\u064a\u0629 \u0662\u0660\u0661\u0668"], "35": ["\u0421\u0432\u044f\u0442\u043e\u0439 \u041d\u0438\u043a\u043e\u043b\u0430\u0439", "Bitcoin Cash", "\u041f\u043e\u0437\u0434\u0440\u0430\u0432\u043b\u0435\u043d\u0438\u044f \u0421 \u041d\u0438\u043a\u043e\u043b\u0430\u0435\u043c", "\u041f\u043e\u0437\u0434\u0440\u0430\u0432\u043b\u0435\u043d\u0438\u0435 \u0421 \u0414\u043d\u0435\u043c \u0421\u0432\u044f\u0442\u043e\u0433\u043e \u041d\u0438\u043a\u043e\u043b\u0430\u044f", "\u041e\u0442\u043a\u0440\u044b\u0442\u0438\u0435 \u0415\u043b\u043a\u0438 \u0412 \u041a\u0438\u0435\u0432\u0435 2017", "\u0434\u0435\u043d\u044c \u0410\u0434\u0432\u043e\u043a\u0430\u0442\u0443\u0440\u0438", "\u0410\u043d\u043d\u0430 \u041a\u0443\u0440\u043d\u0438\u043a\u043e\u0432\u0430", "Feduk", "\u041d\u043e\u0432\u043e\u043b\u0443\u0433\u0430\u043d\u0441\u043a\u043e\u0435", "\u0441 \u0414\u043d\u0435\u043c \u041d\u0438\u043a\u043e\u043b\u0430\u044f", "IKEA", "19 \u0434\u0435\u043a\u0430\u0431\u0440\u044f", "\u0421\u0426\u041a\u041a", "\u0414\u043d\u0435\u043c \u0421\u0432\u044f\u0442\u043e\u0433\u043e \u041d\u0438\u043a\u043e\u043b\u0430\u044f", "\u0421\u0432 \u041c\u0438\u043a\u043e\u043b\u0430\u0439", "\u043d\u043e\u0432\u043e\u0433\u043e\u0434\u043d\u0438\u0435 \u043f\u0440\u0430\u0437\u0434\u043d\u0438\u043a\u0438", "\u0441 \u0414\u043d\u0435\u043c \u0441\u0432\u044f\u0442\u043e\u0433\u043e \u041d\u0438\u043a\u043e\u043b\u0430\u044f", "\u041f\u0440\u0438\u0432\u0456\u0442\u0430\u043d\u043d\u044f \u0417 \u041c\u0438\u043a\u043e\u043b\u0430\u0454\u043c", "\u043f\u043e\u0437\u0434\u0440\u0430\u0432\u043b\u0435\u043d\u0438\u044f \u0441 \u0414\u043d\u0435\u043c \u0441\u0432\u044f\u0442\u043e\u0433\u043e \u041d\u0438\u043a\u043e\u043b\u0430\u044f", "\u0414\u0435\u043d\u044c \u0441\u0432\u044f\u0442\u043e\u0433\u043e \u041d\u0438\u043a\u043e\u043b\u0430\u044f"], "34": ["Carabao Cup", "Manchester City F.c.", "Www Google Com", "Cikgu Azizan", "Jonghyun Funeral", "Han Seo Hee", "Mortal Engines", "lion", "carbon monoxide poisoning", "Jonghyun", "December Global Festivities", "Min Hyo Rin", "allkpop", "Liverpool F.c.", "Taemin", "WWE Clash Of Champions 2017", "Gujarat election", "White", "Manchester City", "Cikgu Azizan"], "33": ["\u0e2b\u0e21\u0e2d\u0e1b\u0e2d", "\u0e02\u0e48\u0e32\u0e27\u0e2b\u0e21\u0e2d\u0e1b\u0e2d", "\u0e25\u0e48\u0e32", "\u0e08\u0e07\u0e2e\u0e22\u0e2d\u0e19", "\u0e2d\u0e32\u0e01\u0e32\u0e28 \u0e27\u0e31\u0e19 \u0e19\u0e35\u0e49", "\u0e2d\u0e32\u0e01\u0e32\u0e28", "\u0e2b\u0e38\u0e49\u0e19\u0e44\u0e17\u0e22", "\u0e44\u0e1b\u0e23\u0e29\u0e13\u0e35\u0e22\u0e4c\u0e44\u0e17\u0e22", "\u0e0a\u0e32\u0e22\u0e19\u0e35\u0e48", "\u0e01\u0e23\u0e21\u0e1e\u0e31\u0e12\u0e19\u0e32\u0e18\u0e38\u0e23\u0e01\u0e34\u0e08\u0e01\u0e32\u0e23\u0e04\u0e49\u0e32", "\u0e15\u0e25\u0e32\u0e14\u0e2b\u0e38\u0e49\u0e19", "\u0e2a\u0e1b\u0e2a\u0e0a", "\u0e2d\u0e38\u0e13\u0e2b\u0e20\u0e39\u0e21\u0e34", "\u0e21\u0e27\u0e22\u0e44\u0e17\u0e227\u0e2a\u0e35", "\u0e25\u0e35\u0e19\u0e48\u0e32\u0e08\u0e31\u0e07", "\u0e15\u0e23\u0e27\u0e08\u0e2b\u0e27\u0e22", "\u0e15\u0e23\u0e27\u0e08 \u0e2b\u0e27\u0e22 16 12 60", "\u0e2b\u0e27\u0e22", "\u0e2a\u0e25\u0e32\u0e01\u0e01\u0e34\u0e19\u0e41\u0e1a\u0e48\u0e07 \u0e23\u0e31\u0e10\u0e1a\u0e32\u0e25", "\u0e15\u0e23\u0e27\u0e08 \u0e2b\u0e27\u0e22"], "32": ["Titanic", "Jorge Almiron", "ganador de Protagonistas 2017", "Pirata de Culiacan", "Anna Kournikova", "Manchester City", "aquel 19", "fiestas navide\u00f1as", "A Otro Nivel", "Jonghyun", "Caracol Tv", "Atletico Nacional", "Caracol", "Churo Diaz", "Ariel Holan", "Felices Fiestas", "Caracoltv", "Santafe", "Campeon Liga Aguila 2017", "Copa Libertadores 2018"], "50": ["Chloe Hammond", "bitcoin cash", "Alma", "Anna Kournikova", "Thor", "Humble Bundle", "Brother Christmas", "Emmerdale 2017", "Patrik Laine", "Veera Ruoho", "Laura Halminen", "Jonghyun", "Ticketmaster", "Black Sabbath", "Emmerdale", "Cast Away", "Hyv\u00e4\u00e4 Joulua", "jul", "Noomi Rapace", "Ashley Jensen"]}