{"42": ["Martin Timell", "Darkest hour", "Britney Spears", "Fouad Saleh", "Agnes Lindstr\u00f6m Bolmgren", "The Shape of Water", "Jovan Rajs", "Alaska", "G\u00f6ransson Arena", "Handbolls Em", "Davos", "Guldbaggegalan", "Amanda Kernell", "Ingmar Bergman", "Hallonbergen", "Aftonbladet Nyheter Idag", "guldbagge", "Sala Allehanda", "Jemen", "Guldbaggegalan 2018"], "43": ["Simon Shelton Barnes", "Berenika Kohoutov\u00e1", "Karel Vo\u0159\u00ed\u0161ek", "DJI Mavic Air", "Niki Lauda", "Tom\u00e1\u0161 Lednik", "Bis", "Tv\u00e1\u0159 vody", "Zeman Barrandov", "Guru J\u00e1ra", "Ov\u010d\u00e1\u010dek", "Neil Diamond", "prezidentsk\u00e1 debata", "Nig\u00e9rie", "Dublin 4", "Gaudeamus", "Heath Ledger", "Man\u017eelsk\u00e9 Etudy Mirka A Anton\u00edn", "Livigno", "Alexis Sanchez"], "49": ["Oscar nominations 2018", "Australian Open 2018", "Wozniacki", "Tonya Harding", "The Square", "Davos", "Black Lightning", "Liverpool", "Shirley MacLaine", "Bitcoin Value", "Christopher Plummer", "Call Me by Your Name", "Elise Mertens", "Kim Ernst", "Morgan Freeman", "Velociraptor", "Phantom Thread", "Connie Sawyer", "Eurosport", "Helena Bonham Carter"], "52": ["Stephen Keshi", "CHAN 2018", "Obasanjo Letter To Buhari", "Alexis S\u00e1nchez", "Liverpool", "Man City", "Hugh Masekela", "Emerson Palmieri", "George Weah", "BUK", "The Chi", "Real Betis vs Barcelona", "Liverpool F.c.", "Lassa Fever", "Real Madrid C.F.", "Chelsea F.c.", "Man City", "Epl Top Scorer", "Aisha Buhari", "Burna Boy Heaven's Gate"], "24": ["E\u015fkiya D\u00fcnyaya H\u00fck\u00fcmdar Olmaz 88 B\u00f6l\u00fcm Izle", "KADIN SON B\u00d6L\u00dcM \u0130ZLE", "GS Store", "ufak tefek cinayetler 13 b\u00f6l\u00fcm", "Lassana Diarra", "Margot Robbie", "SADAT", "Galatasaray", "Nazl\u0131 Kurbanzade", "Musa \u00d6zalkan", "Afrin \u015eehitleri", "Alaska", "S\u00f6z 30 B\u00f6l\u00fcm", "Dilan \u00c7i\u00e7ek Deniz", "siyah beyaz a\u015fk 14 b\u00f6l\u00fcm izle", "mucize", "On Numara Sonu\u00e7lar\u0131 Bug\u00fcn \u00c7ekili\u015f", "The Shape of Water", "Gupse \u00d6zay", "U\u011fur Mumcu"], "25": ["The Shape of Water", "Passport Requirements", "Cavs vs Spurs", "Transport Strike January 24 2018", "Alaska earthquake", "Dfa Online Appointment", "Dfa Passport Renewal", "ESL One Genting", "Pacific Ring of Fire", "Jason Kidd", "Heath Ledger", "Rafael Nadal", "Benham Rise", "SAG Awards 2018", "Mt Pulag", "Jeon Tae Soo", "Mayon Volcano Eruption 2018", "Dua Lipa", "Los Angeles Lakers", "Sergei Eisenstein"], "26": ["Laporte", "Kyle Edmund", "Sevilla Atletico De Madrid", "La forma del agua", "Nadal", "Atletico De Madrid", "La Llamada", "Victor Jara", "Lass Diarra", "Alexis Sanchez", "Nicanor Parra", "Neil Diamond", "Eurovision", "Mascherano", "Eurosport", "Carla Suarez", "Rafinha", "Amazon Go", "Sergei Eisenstein", "Serguei Eisenstein"], "27": ["Piero Angela", "Nicolas Cage", "Constantine", "Paolo Borsellino", "Mascherano", "LIDO CORTESITO", "Carlo Alberto Dalla Chiesa", "Rocco Chinnici", "Oscar 2018", "Chiara Nasti", "Sette Anime", "Cecilia Capriotti", "Beppe Grillo", "La scuola pi\u00f9 bella del mondo", "Nadal", "Terremoto Alaska", "Francesco Bellomo", "Teletubbies", "Craig Warwick", "Giulia Calcaterra"], "21": ["nominados al Oscar 2018", "Olivia Lua", "YosStop", "Sally Hawkins", "Nicanor Parra", "Burro", "Maps Google", "Copa del Rey", "Gary Oldman", "Salvador Zerboni", "Lass Diarra", "Oscars", "Alma Cero", "23 de enero", "Sergei Eisenstein", "poemas", "Alejandra Guzman", "Alaska", "\u00a1que Viva M\u00e9xico!", "Alexis Sanchez"], "48": ["\u03a3\u03b5\u03b9\u03c3\u03bc\u03bf\u03c3 \u0391\u03bb\u03b1\u03c3\u03ba\u03b1", "\u039a\u03c1\u03b9\u03c3\u03b5\u03b9\u03c3 \u0391\u03c3\u03c4\u03c5\u03bd\u03bf\u03bc\u03b9\u03b1\u03c3 2018", "\u039d\u03c4\u03b1\u03b2\u03bf\u03c3", "Anne \u0395\u03c0\u03b5\u03b9\u03c3\u03bf\u03b4\u03b9\u03bf 16", "\u0394\u03b1\u03bb\u03b1\u03ba\u03b1 \u039a\u03b1\u03c4\u03b5\u03c1\u03b9\u03bd\u03b1", "The Shape of Water", "\u039f\u03bb\u03c5\u03bc\u03c0\u03b9\u03b1\u03ba\u03bf\u03c3 \u0391\u03b5\u03ba", "Shape of Water", "Astynomia", "\u0395\u03c5\u03b3\u03b5\u03bd\u03af\u03b1 \u03a3\u03b1\u03bc\u03b1\u03c1\u03ac", "dick pic", "Capital.gr", "1968 \u03a4\u03b1\u03b9\u03bd\u03b9\u03b1", "JASON KIDD", "\u0391\u03bd\u03c4\u03b6\u03c5 \u03a3\u03b1\u03bc\u03b9\u03bf\u03c5", "Survivor 2 \u0395\u03c0\u03b5\u03b9\u03c3\u03bf\u03b4\u03b9\u03bf 2", "Slayer", "\u03a3\u03b5\u03c1\u03b3\u03ba\u03ad\u03b9 \u0391\u03ca\u03b6\u03b5\u03bd\u03c3\u03c4\u03ac\u03b9\u03bd", "Survivor 2", "\u039f\u03bb\u03b3\u03b1 \u03a6\u03b1\u03c1\u03bc\u03b1\u03ba\u03b7"], "23": ["\ucd5c\uc0ac\ub791", "\uad70\ub9c8\ud604", "\ubc15\ud56d\uc11c", "\ud558\uc580\uac70\ud0d1", "\ud3ec\ud2b8\ub098\uc774\ud2b8", "\ud14c\ub2c8\uc2a4", "\uc870\uc724\uc120", "\ubc15\uc2e0\uc601", "\ub098\ub2ec", "\uc167\ub2e4\uc6b4", "\uc804\ud0dc\uc218", "\uc815\ud604", "\uc815\ud604 \ud14c\ub2c8\uc2a4 \uc911\uacc4", "\uae40\uc900\ud638", "\ud55c\ube44\uc57c", "\ud604\uc1a1\uc6d4", "\ubbf8\uc624\uce58\uce58 \uc740\uac00\ub204", "\uc1a1\ud574", "UFC", "\ubc15\ud56d\uc11c"], "46": ["Sarah Fraisou", "Pascal Cardonna", "Hugh Masekela", "Gone", "Klaus Schwab", "Venoge Festival", "Nadal", "Schladming", "DJI Mavic Air", "WEF", "The Shape of Water", "Kronplatz", "Tsunami", "Oscar Nominations 2018", "Kyle Edmund", "Europa-Park", "Jenny Frankhauser", "Gotthard Tunnel", "Tina York", "Natascha Ochsenknecht"], "47": ["Mascherano", "Margot Robbie", "Germana T\u00e2nger", "Oscars 2018", "Nomeados Oscares 2018", "Alasca", "Argentina", "Darkest Hour", "Madonna", "Mo\u00e7ambique", "India", "Mercadona", "Davos", "CNN", "The Post", "Ta\u00e7a CTT", "Lassana Diarra", "Muro das Lamenta\u00e7\u00f5es", "Nadal", "DJI"], "44": ["Felix Neureuther", "Condor", "Udo Landbauer", "Shape of Water", "Jenny Frankhauser", "Laura Moisl", "DJI", "Orf Programm", "Nadal", "Tina York", "Sankt Maik", "Neil Diamond", "Hope Hicks", "Natascha Ochsenknecht", "Psn Status", "Christian Hirschb\u00fchl", "Ich Bin Ein Star Holt Mich Hier Raus 2018", "Trevor Traina", "Freimaurer", "Planai"], "45": ["Kern Andr\u00e1s", "Neil Diamond", "testr\u0151l \u00e9s l\u00e9lekr\u0151l", "Lidl \u00c1ll\u00e1s", "Cserpes Laura", "A v\u00edz \u00e9rint\u00e9se", "Nadal", "Borb\u00e9ly Alexandra", "Helen Mirren", "Kim Wall", "Cooky", "T\u0151k\u00e9czki L\u00e1szl\u00f3", "Davos", "Volt 2018", "Kadarkai Endre", "Liverpool", "Fucsovics M\u00e1rton", "Sziget 2018", "Endometri\u00f3zis", "tenisz"], "28": ["Vnexpress 24h", "Xem Lai Bong Da", "Co Dong Vien Viet Nam", "c\u1ed5 v\u0169 b\u00f3ng \u0111\u00e1", "Nguy\u1ec5n V\u0103n To\u00e0n", "\u0110\u1ee9c Chinh", "Nh\u01b0 C\u00f3 B\u00e1c H\u1ed3 Trong Ng\u00e0y Vui \u0110\u1ea1i Th\u1eafng", "V\u0169 \u0110\u1ee9c \u0110am", "VOV", "B\u00f9i Ti\u1ebfn D\u0169ng", "Uzbekistan", "Vtv Go", "24h Bong Da", "Fpt Play", "VTV3", "Xem Tivi", "Vnexpress Th\u1ec3 Thao", "Muhammad Taqi", "Afc U23 Championship 2018", "Truyen Hinh Truc Tuyen Vtv6"], "29": ["\u0646\u062a\u064a\u062c\u0647 \u0627\u0644\u0637\u0644\u0627\u0628", "\u0645\u0627\u0646\u0634\u0633\u062a\u0631 \u0633\u064a\u062a\u064a", "\u0627\u062e\u0631 \u0627\u0644\u0627\u062e\u0628\u0627\u0631", "\u0646\u062a\u064a\u062c\u0647 \u0627\u0644\u0634\u0647\u0627\u062f\u0647 \u0627\u0644\u0627\u0639\u062f\u0627\u062f\u064a\u0647 \u0645\u062d\u0627\u0641\u0638\u0647 \u0627\u0644\u0642\u0627\u0647\u0631\u0647", "the Shape of Water", "\u0633\u0627\u0645\u064a \u0639\u0646\u0627\u0646", "\u0644\u064a\u0641\u0631\u0628\u0648\u0644", "\u0643\u0648\u0631\u0629 \u0644\u0627\u064a\u0641", "\u0646\u062a\u064a\u062c\u0629 \u0627\u0644\u0634\u0647\u0627\u062f\u0629 \u0627\u0644\u0627\u0639\u062f\u0627\u062f\u064a\u0629 \u0628\u0631\u0642\u0645 \u0627\u0644\u062c\u0644\u0648\u0633", "\u0627\u0639\u062a\u0642\u0627\u0644 \u0633\u0627\u0645\u064a \u0639\u0646\u0627\u0646", "\u062e\u0627\u0644\u062f \u0639\u0644\u064a", "\u0628\u0648\u0627\u0628\u0629 \u0646\u062a\u0627\u0626\u062c \u0627\u0644\u062a\u0639\u0644\u064a\u0645 \u0627\u0644\u0627\u0633\u0627\u0633\u0649 2018", "\u0648\u0632\u0627\u0631\u0647 \u0627\u0644\u062a\u0631\u0628\u064a\u0647 \u0648\u0627\u0644\u062a\u0639\u0644\u064a\u0645", "\u0644\u064a\u0641\u0631\u0628\u0648\u0644 \u0648\u0633\u0648\u0627\u0646\u0632\u0649 \u0633\u064a\u062a\u0649", "\u063a\u0627\u062f\u0629 \u0648\u0627\u0644\u064a", "\u0627\u062d\u0645\u062f \u0627\u0644\u0639\u0634", "\u0646\u064a\u0633\u0627\u0646", "\u0628\u062b \u0645\u0628\u0627\u0634\u0631", "\u0628\u064a\u0627\u0646 \u0633\u0627\u0645\u0649 \u0639\u0646\u0627\u0646 \u0627\u0644\u0627\u062e\u064a\u0631", "\u0633\u062a\u0627\u0646\u0644\u064a"], "40": ["Man City", "Hugh Masekela", "Aka Star Signs", "Liverpool", "Ayanda Dlodlo", "Liverpool FC", "Oscar Nominations 2018", "Alexis S\u00e1nchez", "Anoj Singh", "Bathabile Dlamini", "Nadal", "Princess Eugenie", "Krugersdorp News", "Qedani Mahlangu", "Krugersdorp", "George Weah", "Google Classroom", "Kaizer Chiefs News Now", "Cyril Ramaphosa Jacob Zuma", "Real Madrid"], "41": ["Jupiler Pro League", "PSN", "STVV", "Kaat Thuis", "Elise Mertens", "Tinky Winky", "The Shape of Water", "Shania Gooris", "Wozniacki", "PlayStation", "Blind Getrouwd", "Nadal", "Neil Diamond", "Britney Spears", "Alaska", "DJI", "Davos", "Patser Film", "Frites Atelier Amsterdam | Antwerpen", "La Villa Des Coeurs Bris\u00e9s 3 Episode 32"], "1": ["Oscar Nominations 2018", "Alaska earthquake", "Call Me by Your Name", "Phantom Thread", "Lady Bird", "LeBron James", "Tammy Duckworth", "Nadal", "Jalen Ramsey", "PlayStation Network", "DJI", "Ursula Le Guin", "Jason Momoa", "Rosie the Riveter", "Genie Bouchard", "Mudbound", "Kevin Love", "Melania Trump", "Dunkirk", "Davos"], "3": ["Padmavat", "Ratha Saptami", "Darkest Hour", "Jio Republic Day offer", "Neet Pg 2018 Result", "Nadal", "The Shape of Water", "NBE", "23 January", "Sanya Sagar", "Liverpool", "Cate Blanchett", "Alexis S\u00e1nchez", "ACCUWEATHER", "Praful Bhalerao", "Weather Delhi", "Subhash Chandra Bose Birthday", "Sergei Eisenstein", "Subhash Chandra Bose", "SpiceJet"], "5": ["Mavic Air", "Aubameyang", "Simon Shelton Barnes", "Man City", "Phantom Thread", "Enzo Amore", "Jakarta earthquake", "earthquake today", "The Shape Of Water", "Nadal", "Alexis S\u00e1nchez", "Federer", "Tom Brady", "Liverpool F.c.", "Davos", "Jonghyun", "Black Lightning", "Princess Eugenie", "Dfa Online Appointment", "Sgx Singapore"], "4": ["\u677e\u6751\u6c99\u53cb\u7406", "\u82b1\u306e\u3061\u6674\u308c", "\u5fa1\u5dbd\u5c71", "\u7530\u4e2d\u307f\u306a\u5b9f", "\u8349\u6d25\u767d\u6839\u5c71", "\u4e38\u5ca1\u3044\u305a\u307f", "\u4f4f\u5409\u90fd", "\u5730\u9707", "\u5c71\u5d0e\u8ce2\u4eba", "\u677e\u5742\u5927\u8f14", "\u4f50\u85e4\u30a8\u30ea", "\u91d1\u7530\u4e00 37 \u6b73", "\u5927\u5ddd\u5b8f\u6d0b", "\u76f8\u9244\u30d0\u30b9", "\u9996\u90fd\u9ad8", "FFBE", "\u96ea\u304b\u304d", "\u96ea\u3060\u308b\u307e", "\u83c5\u4e95\u53cb\u9999", "\u30db\u30ea\u30c7\u30a4\u30e9\u30d6"], "6": ["\u05e2\u05d4\u05d3 \u05ea\u05de\u05d9\u05de\u05d9", "\u05d3\u05d0\u05d1\u05d5\u05e1", "\u05e4\u05e8\u05e9\u05ea \u05d4\u05de\u05df", "\u05d9\u05d4\u05d5\u05e0\u05ea\u05df \u05d2\u05e4\u05df", "\u05de\u05d0\u05d9\u05e8 \u05d1\u05e0\u05d0\u05d9", "Oscar Nominations 2018", "\u05d1\u05d9\u05ea\u05e8 \u05d9\u05e8\u05d5\u05e9\u05dc\u05d9\u05dd \u05e0\u05d2\u05d3 \u05d1\u05e0\u05d9 \u05e1\u05db\u05e0\u05d9\u05df", "\u05d0\u05dc\u05db\u05e1\u05d9\u05e1 \u05e1\u05d0\u05e0\u05e6'\u05e1", "Alexis Sanchez", "\u05de\u05d5\u05d8\u05d9 \u05d9\u05d5\u05d2\u05d1", "\u05e1\u05e8\u05d2\u05d9\u05d9 \u05d0\u05d9\u05d9\u05d6\u05e0\u05e9\u05d8\u05d9\u05d9\u05df", "Sergei Eisenstein", "\u05d1\u05d9\u05ea\u05e8 \u05d9\u05e8\u05d5\u05e9\u05dc\u05d9\u05dd", "\u05d4\u05e8\u05d1 \u05e0\u05d9\u05e1\u05d9\u05dd \u05de\u05d5\u05d9\u05d0\u05dc", "\u05d1\u05d9\u05ea \u05e8 \u05d9\u05e8\u05d5\u05e9\u05dc\u05d9\u05dd", "Mike Pence", "\u05d3\u05e4\u05e0\u05d4 \u05d3\u05e7\u05dc", "\u05de\u05d0\u05d5\u05e8 \u05de\u05dc\u05d5\u05dc", "\u05d0\u05e0\u05e8\u05d9\u05e7\u05d4 \u05d0\u05d9\u05d2\u05dc\u05e1\u05d9\u05d0\u05e1 \u05d1\u05d9\u05e9\u05e8\u05d0\u05dc", "\u05e8\u05d9\u05d0\u05dc \u05de\u05d3\u05e8\u05d9\u05d3"], "9": ["Nta Winners", "Oscar nominations 2018", "Nta Awards 2018", "Man City", "Kyle Edmund", "23rd National Television Awards Nominees And Winners", "tsunami", "Simon Shelton", "Britney Spears", "David Attenborough", "Danny Walters", "Neil Diamond", "Peter Kay", "Nadal", "Enzo Amore", "Black Lightning", "Phantom Thread", "Hugh Masekela", "Call Me by Your Name", "Australian Open Tennis 2018"], "8": ["Sydney Trains", "Caroline Wozniacki", "Margot Robbie", "Mavic Air", "Phantom Thread", "Enzo Amore", "Brisbane Roar", "Jennifer Aniston", "Ursula Le Guin", "SuperCoach", "Mount Kusatsu-Shirane", "Macaulay Culkin", "David Lee", "Nadal", "Kyle Edmund", "Neil Diamond", "Oscar Nominations 2018", "earthquake today", "Bankstown shooting", "Svitolina"], "51": ["Norwegian Family", "Magnus Krogs\u00e6ter Aarre", "Joe Erling Jahr", "Britney Spears", "The Shape of Water", "Simon Shelton", "Ida Lindtveit R\u00f8se", "Henrik Kristoffersen", "Ragnhild Mowinckel", "tsunami", "Schladming", "Svartedauden", "Lux Wright", "Kitty Kat West", "Huseiernes Landsforbund", "Davos", "border collie", "Ada Hegerberg", "Swansea", "Henrik Ibsens gate 4"], "39": ["24 Ianuarie 1859", "Marea Unire", "Nae Nicolae", "Lassana Diarra", "Unirea Principatelor", "Calendar Ortodox Ianuarie 2018", "Nadal", "FRUCTUL OPRIT EPISODUL 2", "The shape of water", "Cutremur Alaska", "Wozniacki", "Ozana Barabancea", "Svitolina", "Davos", "Oana Zavoranu", "Cand Joaca Halep", "CCR", "Aspazia Otel Petrescu", "Unirea Mica", "Mobile Ro"], "38": ["Nicanor Parra", "Gabinete Pi\u00f1era 2018", "Terremoto en Alaska", "Marcelo Romo", "Gerardo Varela", "Hernan Larrain", "Roberto Ampuero", "Isabel Pla", "Emilio Santelices", "Alejandra Perez", "Nominaciones Oscar 2018", "Una Mujer Fantastica", "Pauline Kantor", "Marcela Cubillos", "Daniela Vega", "Antonio Walker", "Alfredo Moreno", "Gonzalo Blumel", "Juan Andres Fontaine", "Gloria Hutt"], "10": ["\u814a\u516b\u8282", "\u5fd8\u5f62\u6c34", "Tizzy Bac", "\u7fa4\u99ac", "Dji", "\u8349\u6d25", "\u6881\u6f22\u6587", "\u7121\u9593\u9053 Tvb", "\u6a02\u77b3", "\u6771\u4eac", "\u6771\u9435", "\u963f\u62c9\u65af\u52a0", "\u8607\u97fb\u59ff", "\u6210\u7530\u6a5f\u5834", "\u6797\u904e\u96f2", "\u6cb3\u667a\u82d1", "\u912d\u82e5\u9a4a", "\u5c71\u982d \u6587\u5316", "\u6881\u5929\u7426", "\u9678\u6c38"], "13": ["Britney Spears", "Tsunami Warning Vancouver", "Oscar Nominations 2018", "Toronto Maple Leafs", "Commission Scolaire De La Capitale", "Neil Diamond", "Tva Nouvelles", "Psn Status", "\u00c9cole Ferm\u00e9", "Stephanie Katelnikoff", "Meteo", "Phantom Thread", "Call Me by Your Name", "Nadal", "Lady Bird", "\u00e9coles ferm\u00e9es", "Black Lightning", "Mavic Air", "The Keg", "Kentucky shooting"], "12": ["\u706b\u8eca\u8a02\u7968", "\u6c34\u5e95\u60c5\u6df1", "\u81d8\u516b\u7ca5", "\u5730\u9707", "\u7fa4\u806f", "\u8349\u6d25\u767d\u6839\u5c71", "\u674e\u9032\u826f", "\u5f35\u5584\u70ba", "\u9418\u9249", "\u81d8\u516b", "\u5927\u6a02\u900f\u865f\u78bc", "\u83ef\u56fa\u5967\u4e4b\u677e", "\u65bd\u5ba3\u6995", "\u6293\u9f8d\u7b4b", "\u5f6d\u4f73\u6167", "\u9ec3\u52dd\u96c4", "731\u90e8\u968a", "\u6797\u5229\u970f", "\u53f0\u9435", "\u5f8c\u85e4\u5e0c\u7f8e\u5b50"], "15": ["Simon Shelton Barnes", "Chryssanthi Kavazi", "Britney Spears", "L\u00fcnen", "Jenny Frankhauser", "Tina York", "The Shape of Water", "2 Bundesliga", "Natascha Ochsenknecht", "DJI Mavic Air", "Niki Lauda", "Sankt Maik", "PSN", "Fack Ju G\u00f6hte", "Alaska", "Mike Singer", "Nadal", "Schladming", "Maite Kelly", "Holstein Kiel"], "14": ["\u0410\u0440\u0442\u0435\u043c \u0418\u0441\u0445\u0430\u043a\u043e\u0432", "\u0420\u043e\u0439\u0437\u043c\u0430\u043d", "\u0421\u043c\u0435\u0440\u0442\u044c \u0421\u0442\u0430\u043b\u0438\u043d\u0430", "\u041d\u0435\u043b\u044e\u0431\u043e\u0432\u044c", "\u0425\u0430\u043d\u043d\u0430", "\u041c\u0430\u0441\u043b\u0435\u043d\u0438\u0446\u0430 2018", "\u041f\u043e\u0433\u043e\u0434\u0430 \u0422\u044e\u043c\u0435\u043d\u044c", "\u041f\u043e\u0433\u043e\u0434\u0430 \u0432 \u0422\u044e\u043c\u0435\u043d\u0438", "\u041d\u0430\u0442\u0430\u043b\u044c\u044f \u0421\u0435\u043b\u0435\u0437\u043d\u0435\u0432\u0430", "\u0428\u0430\u0438\u043d\u0441\u043a\u0438\u0439", "\u0412\u0435\u0440\u0441\u0442\u043e\u0432", "\u041a\u043e\u0433\u0434\u0430 \u041c\u0430\u0441\u043b\u0435\u043d\u0438\u0446\u0430", "\u0420\u0435\u0430\u043b \u041c\u0430\u0434\u0440\u0438\u0434", "\u041c\u0438\u043e\u0447\u0438\u0447 \u041d\u0433\u0430\u043d\u043d\u0443", "\u0412\u044b\u0441\u043e\u0446\u043a\u0438\u0439", "21 \u044f\u043d\u0432\u0430\u0440\u044f", "\u041c\u0430\u043d\u0447\u0435\u0441\u0442\u0435\u0440 \u042e\u043d\u0430\u0439\u0442\u0435\u0434", "\u0415\u0432\u0433\u0435\u043d\u0438\u044f \u041c\u0435\u0434\u0432\u0435\u0434\u0435\u0432\u0430", "\u0420\u0443\u043a\u0438 \u0411\u0430\u0437\u0443\u043a\u0438", "\u041f\u0440\u0438\u043a\u043b\u044e\u0447\u0435\u043d\u0438\u044f \u041f\u0430\u0434\u0434\u0438\u043d\u0433\u0442\u043e\u043d\u0430 2"], "17": ["DJI Mavic Air", "Koen Everink", "Neil Diamond", "The Shape of Water", "Tinky Winky", "Paal 14", "PlayStation", "Ed Sheeran", "Nadal", "Black Lightning", "Liza Sips", "Elise Mertens", "Olympische Winterspelen", "Kijkshop", "Luizenmoeder", "Ronnie Flex", "Luizenmoeder Gemist", "Lux Wright", "Heath Ledger", "Robin van Persie"], "16": ["Daniel Moquet", "Miss Sloane", "Canet Caen", "Bruno Guillon", "Gone", "La Mie Caline", "tsunami", "RER C", "Kim Wall", "Nadal", "Melanie Et Benjamin", "Candide Thovex", "Alexandre Bompard", "Anthony Delon", "Danny Pino", "PSN", "Jawad Bendaoud", "Rescue Dawn", "Nantes Auxerre", "Nagui"], "19": ["Maze Runner", "The Shape of Water", "Penyebab Gempa Bumi", "Gerhana Bulan", "Copa del Rey", "Gempa Hari Ini", "Gempa Jakarta", "Sys NS", "Detiknews", "Gempa Banten", "Detik.com", "Alexis Sanchez", "Bali United vs Chiangrai", "Gempa Baru Saja", "Persebaya", "Jakarta Gempa", "Gempa Bumi 23 Januari 2018", "Apartemen Margonda Miring", "Pusat Gempa Baru Saja", "Cornelia Agatha"], "18": ["Globocop", "A Forma Da Agua", "Mariana D'\u00e1vila", "Raio Negro", "Aline Cristina Bbb", "Lassana Diarra", "Me Chame pelo Seu Nome", "Teletubbies", "G1 PE", "Manchester City", "terremoto no Alasca", "Giovanna Grigio", "Lady Bird", "Virtus", "Enem Resultado", "Lula Preso", "SED", "Macaulay Culkin", "God Of War", "Pronatec"], "31": ["Jaros\u0142aw Jach", "Nadal", "Nominacje Do Oscara 2018", "Dzwon ratowniczy", "Kszta\u0142t wody", "Iga Krefft", "Jan Traczyk", "Liga Narod\u00f3w", "Helena Englert", "Kazimierz i Kleparz", "Lady Bird", "Lassana Diarra", "Kleparz", "23 stycznia", "M Jak Mi\u0142o\u015b\u0107 1346", "Juventus", "Ma\u0142gorzata Gersdorf", "Ni\u0107 widmo", "Lech Tv", "faszyzm"], "30": ["Temporal en Mar del Plata", "Copa Argentina", "Copa Argentina 2018", "Lady Bird", "Spinetta", "La forma del agua", "Pablo Aimar", "Nadal", "Teletubbies", "Angela Torres", "El Trece", "Bruno Zuculini", "Rompehielos Irizar", "Nicanor Parra", "Luciano Pereyra", "Nicole Neumann", "Gast\u00f3n Pauls", "Bernardo Alcanoni", "Precio Del Dolar Hoy", "Juliana Awada"], "37": ["Man City", "Newport Fc", "Atletico Madrid", "Alexis S\u00e1nchez", "Liverpool FC", "Hugh Masekela", "Sevilla Fc", "Eric Omondi challenge", "Eric Omondi", "Charles Njonjo", "Nantes Fc", "Celtic Fc", "Alfred Keter", "Lincoln Fc", "Emerson Palmieri", "Shrewsbury Fc", "Liverpool", "Anita Nderu", "Juventus", "George Weah"], "36": ["\u0627\u0644\u062a\u0634\u063a\u064a\u0644 \u0627\u0644\u0630\u0627\u062a\u064a", "\u0645\u0627\u0646\u0634\u0633\u062a\u0631 \u0633\u064a\u062a\u064a", "\u0648\u0632\u0627\u0631\u0629 \u0627\u0644\u0635\u062d\u0629", "\u0645\u062d\u0645\u062f \u0627\u0644\u0645\u0641\u0631\u062d", "\u0633\u0627\u0645\u064a \u0639\u0646\u0627\u0646", "\u0645\u0648\u062f\u064a", "\u0633\u0646\u0627\u0628", "\u0644\u064a\u0641\u0631\u0628\u0648\u0644", "\u0627\u0634\u0631\u0641 \u0628\u0646 \u0634\u0631\u0642\u064a", "\u0645\u0628\u0627\u0631\u0627\u0629 \u0644\u064a\u0641\u0631\u0628\u0648\u0644 \u0627\u0644\u064a\u0648\u0645", "\u0645\u0639\u0644\u0645 \u0627\u0644\u0627\u062d\u0633\u0627\u0621", "\u0646\u064a\u0641\u064a\u0632", "\u0627\u0644\u0645\u0644\u0643 \u0639\u0628\u062f\u0627\u0644\u0644\u0647", "the Shape of Water", "\u0633\u0627\u0646\u0634\u064a\u0632", "Liverpool", "\u0627\u0639\u062a\u0642\u0627\u0644 \u0633\u0627\u0645\u064a \u0639\u0646\u0627\u0646", "\u0645\u0628\u0627\u0631\u0627\u0629 \u0644\u064a\u0641\u0631\u0628\u0648\u0644", "\u0646\u064a\u0633\u0627\u0646", "\u062f\u0627\u0641\u0648\u0633"], "35": ["\u0414\u0438\u0444\u0442\u0435\u0440\u0456\u044f", "\u041e\u0441\u043a\u0430\u0440 2018", "\u0448\u043a\u043e\u043b\u0430", "\u0420\u043e\u0439\u0437\u043c\u0430\u043d", "\u0421\u043c\u0435\u0440\u0442\u044c \u0421\u0442\u0430\u043b\u0438\u043d\u0430", "\u0410\u0440\u0442\u0435\u043c \u0418\u0441\u0445\u0430\u043a\u043e\u0432", "\u0421\u0435\u0440\u0433\u0435\u0439 \u042d\u0439\u0437\u0435\u043d\u0448\u0442\u0435\u0439\u043d", "\u0428\u043a\u043e\u043b\u0430 11 \u0421\u0435\u0440\u0456\u044f", "22 \u0441\u0456\u0447\u043d\u044f", "22 \u044f\u043d\u0432\u0430\u0440\u044f", "\u041f\u043e\u0440\u043e\u0448\u0435\u043d\u043a\u043e \u041c\u0430\u043b\u044c\u0434\u0438\u0432\u044b", "\u0414\u0435\u043d\u044c \u0421\u043e\u0431\u043e\u0440\u043d\u043e\u0441\u0442\u0456 \u0423\u043a\u0440\u0430\u0457\u043d\u0438", "\u0434\u0435\u043d\u044c \u043e\u0431\u0456\u0439\u043c\u0456\u0432", "\u041a\u0430\u0431\u0443\u043b", "\u0420\u0435\u0430\u043b \u041c\u0430\u0434\u0440\u0438\u0434", "\u041a\u043e\u043d\u0441\u0442\u0430\u043d\u0442\u0438\u043d", "\u0421\u0432\u0438\u0442\u043e\u043b\u0438\u043d\u0430", "\u0432 \u0448\u043a\u043e\u043b\u0435", "\u0414\u0435\u043d\u044c \u043e\u0431\u044a\u044f\u0442\u0438\u0439", "\u0418\u0440\u0438\u043d\u0430 \u0411\u0438\u043b\u044b\u043a"], "34": ["Aubameyang", "The Shape of Water", "Mavic Air", "Carabao Cup", "Jdt Vs Muangthong United 2018", "Jakarta earthquake", "Alexis S\u00e1nchez", "earthquake today", "Liverpool F.c.", "ESL One Genting", "Nadal", "Swansea vs Liverpool", "Mkhitaryan", "JDT", "Ha Ji Won", "Real Madrid", "Jeon Tae Soo", "Jun Tae Soo", "Djokovic", "dark web"], "33": ["\u0e40\u0e21\u0e37\u0e2d\u0e07\u0e17\u0e2d\u0e07", "\u0e40\u0e0a\u0e35\u0e22\u0e07\u0e23\u0e32\u0e22 \u0e22\u0e39\u0e44\u0e19\u0e40\u0e15\u0e47\u0e14", "\u0e1b\u0e23\u0e32\u0e1a \u0e15\u0e4c \u0e1b\u0e0e\u0e25 \u0e2a\u0e38\u0e27\u0e23\u0e23\u0e13 \u0e1a\u0e32\u0e07", "\u0e02\u0e27\u0e31\u0e0d \u0e2d\u0e38\u0e29\u0e32 \u0e21\u0e13\u0e35", "\u0e41\u0e21\u0e48\u0e2d\u0e32\u0e22 \u0e2a\u0e30\u0e2d\u0e37\u0e49\u0e19", "James Palumbo", "\u0e22\u0e37\u0e48\u0e19 \u0e20\u0e32\u0e29\u0e35 2560", "\u0e23\u0e31\u0e0a\u0e19\u0e01 \u0e2d\u0e34\u0e19\u0e17\u0e19\u0e19\u0e17\u0e4c", "\u0e15\u0e32\u0e23\u0e32\u0e07 \u0e1e\u0e23\u0e35\u0e40\u0e21\u0e35\u0e22\u0e23\u0e4c \u0e25\u0e35\u0e01", "\u0e15\u0e49\u0e2d\u0e21 \u0e02\u0e32\u0e22\u0e2b\u0e31\u0e27\u0e40\u0e23\u0e32\u0e30", "\u0e0a\u0e19\u0e32\u0e18\u0e34\u0e1b \u0e2a\u0e23\u0e07\u0e01\u0e23\u0e30\u0e2a\u0e34\u0e19\u0e18\u0e4c", "\u0e40\u0e21\u0e22\u0e4c \u0e23\u0e31\u0e0a\u0e19\u0e01", "\u0e40\u0e1e\u0e0a\u0e23 \u0e2a\u0e2b \u0e23\u0e31\u0e15\u0e19\u0e4c", "\u0e15\u0e31\u0e4a\u0e01\u0e41\u0e15\u0e19", "\u0e15\u0e31\u0e4a\u0e01\u0e41\u0e15\u0e19 \u0e40\u0e1e\u0e0a\u0e23", "\u0e44\u0e02\u0e48\u0e41\u0e21\u0e27", "\u0e02\u0e48\u0e32\u0e27\u0e2b\u0e27\u0e2230\u0e25\u0e49\u0e32\u0e19", "\u0e40\u0e08 \u0e40\u0e21 \u0e22\u0e4c", "\u0e40\u0e21\u0e22\u0e4c \u0e1e\u0e34\u0e0a\u0e0d\u0e4c\u0e19\u0e32\u0e0f", "\u0e40\u0e08 \u0e0a\u0e19\u0e32 \u0e18\u0e34 \u0e1b"], "32": ["Terremoto En Alaska Hoy", "La forma del agua", "Nadal", "Copa del Rey", "Amaranta Hank", "Nicanor Parra", "Censo 2018", "Laura Acu\u00f1a", "Manchester City", "Lass Diarra", "Sergei Eisenstein", "America Vs Cali", "Claudia Morales", "Heath Ledger", "Juan Fernando Quintero", "Federer", "Clara Lopez", "Morgan Freeman", "Jaime Garzon", "Boca vs River"], "50": ["Call Me by Your Name", "The Shape of Water", "Kim Wall", "CNN", "OneCoin", "Alaska", "Poldark", "Black Lightning", "Peyronie's Disease", "AKT", "Periscope", "Kaya Scodelario", "Sak", "Charissa Thompson", "Flow Festival 2018", "Maze Runner", "Super Bowl 2018", "Heath Ledger", "Listeria", "Flow"]}